pystolint/__init__.py
pystolint/__main__.py
pystolint/api.py
pystolint/main.py
pystolint/tools.py
pystolint/version.py
pystolint/default_config/pyproject.toml
pystolint/dto/__init__.py
pystolint/dto/report.py
pystolint/mypy/__init__.py
pystolint/mypy/deprecated_plugin.py
pystolint/mypy/mypy_check.py
pystolint/ruff/__init__.py
pystolint/ruff/ruff_check.py
pystolint/ruff/ruff_format.py
pystolint/util/__init__.py
pystolint/util/git.py
pystolint/util/paths.py
pystolint/util/toml.py
pystolint-0.6.1.dist-info/licenses/LICENSE
pystolint-0.6.1.dist-info/METADATA
pystolint-0.6.1.dist-info/WHEEL
pystolint-0.6.1.dist-info/entry_points.txt
pystolint-0.6.1.dist-info/top_level.txt
pystolint-0.6.1.dist-info/RECORD
