Metadata-Version: 2.4
Name: pystolint
Version: 0.6.1
Summary: Linters composer
Author-email: Leonid Vinogradov <lugod.a30@gmail.com>
Project-URL: Changelog, https://github.com/hhru/pystolint/blob/master/CHANGELOG.md
Project-URL: Homepage, https://github.com/hhru/pystolint
Project-URL: Source, https://github.com/hhru/pystolint
Requires-Python: >=3.9
License-File: LICENSE
Requires-Dist: mypy==1.15.0
Requires-Dist: poetry-core<3,>=2
Requires-Dist: ruff==0.11.6
Requires-Dist: tomli==2.2.1; python_version == "3.9"
Requires-Dist: tomli-w==1.2.0
Provides-Extra: test
Requires-Dist: pytest==8.3.5; extra == "test"
Provides-Extra: pydantic
Requires-Dist: pydantic<3,>=2.1; extra == "pydantic"
Dynamic: license-file
